update_checker_app/__init__.py
update_checker_app/controllers.py
update_checker_app/helpers.py
update_checker_app/models.py
update_checker_app-0.6.dist-info/DESCRIPTION.rst
update_checker_app-0.6.dist-info/METADATA
update_checker_app-0.6.dist-info/RECORD
update_checker_app-0.6.dist-info/WHEEL
update_checker_app-0.6.dist-info/entry_points.txt
update_checker_app-0.6.dist-info/metadata.json
update_checker_app-0.6.dist-info/top_level.txt
