Metadata-Version: 2.0
Name: update-checker-app
Version: 0.6
Summary: Flask Application that provides the interface to the update_checker package.
Home-page: https://github.com/bboe/update_checker_app
Author: Bryce Boe
Author-email: bbzbryce@gmail.com
License: Simplified BSD License
Keywords: python packages,update check
Platform: UNKNOWN
Classifier: Intended Audience :: Developers
Classifier: License :: OSI Approved :: BSD License
Classifier: Operating System :: OS Independent
Classifier: Programming Language :: Python
Requires-Dist: flask (>=0.10.1,<1)
Requires-Dist: flask-sqlalchemy (>=2.1,<3)
Requires-Dist: psycopg2 (<3,>=2.6.1)
Requires-Dist: requests (>=2.8.1,<3)
Requires-Dist: update-checker (>=0.11,<1)
